structpca/__init__.py
structpca/_utils.py
structpca/model.py
structpca/__pycache__/__init__.cpython-310.pyc
structpca/__pycache__/model.cpython-310.pyc
structpca-0.0.11.dist-info/LICENSE
structpca-0.0.11.dist-info/METADATA
structpca-0.0.11.dist-info/WHEEL
structpca-0.0.11.dist-info/top_level.txt
structpca-0.0.11.dist-info/RECORD
