Metadata-Version: 2.1
Name: structpca
Version: 0.0.11
Summary: Structured Principal Component Analysis
Author-email: Bastien Batardière <bastien.batardiere@gmail.com>
Maintainer-email: Bastien Batardière <bastien.batardiere@gmail.com>
License: MIT License
Classifier: License :: OSI Approved :: MIT License
Classifier: Development Status :: 3 - Alpha
Classifier: Programming Language :: Python
Requires-Python: >=3.7
License-File: LICENSE
Requires-Dist: numpy
Provides-Extra: doc
Requires-Dist: sphinx ; extra == 'doc'
Requires-Dist: sphinx-rtd-theme ; extra == 'doc'
Provides-Extra: tests
Requires-Dist: pytest ; extra == 'tests'
Requires-Dist: pytest-lazy-fixture ; extra == 'tests'
